qiskit_serverless/VERSION.txt
qiskit_serverless/__init__.py
qiskit_serverless/exception.py
qiskit_serverless/version.py
qiskit_serverless/core/__init__.py
qiskit_serverless/core/client.py
qiskit_serverless/core/constants.py
qiskit_serverless/core/decorators.py
qiskit_serverless/core/enums.py
qiskit_serverless/core/files.py
qiskit_serverless/core/function.py
qiskit_serverless/core/job.py
qiskit_serverless/core/local_functions_store.py
qiskit_serverless/core/tracing.py
qiskit_serverless/core/clients/__init__.py
qiskit_serverless/core/clients/local_client.py
qiskit_serverless/core/clients/ray_client.py
qiskit_serverless/core/clients/serverless_client.py
qiskit_serverless/serializers/__init__.py
qiskit_serverless/serializers/program_serializers.py
qiskit_serverless/serializers/serializers.py
qiskit_serverless/utils/__init__.py
qiskit_serverless/utils/errors.py
qiskit_serverless/utils/formatting.py
qiskit_serverless/utils/http.py
qiskit_serverless/utils/json.py
qiskit_serverless/utils/runtime_service_client.py
qiskit_serverless/utils/urls.py
qiskit_serverless/visualization/__init__.py
qiskit_serverless/visualization/widget.py
tests/__init__.py
tests/utils.py
tests/core/__init__.py
tests/core/test_decorator.py
tests/core/test_ibm_serverless_client.py
tests/core/test_job.py
tests/core/test_pattern.py
tests/resources/job.py
tests/serializers/__init__.py
tests/serializers/test_program_serializers.py
qiskit_serverless-0.26.1.dist-info/METADATA
qiskit_serverless-0.26.1.dist-info/WHEEL
qiskit_serverless-0.26.1.dist-info/top_level.txt
qiskit_serverless-0.26.1.dist-info/RECORD
