Metadata-Version: 2.1
Name: qiskit-serverless
Version: 0.26.1
Summary: An open-source SDK for resource management in quantum computing workflows.
Author-email: Qiskit Serverless Team <qiskit@us.ibm.com>
License: Apache 2.0
Keywords: qiskit,serverless,quantum computing
Classifier: Development Status :: 3 - Alpha
Classifier: Intended Audience :: Developers
Classifier: Intended Audience :: Science/Research
Classifier: License :: OSI Approved :: Apache Software License
Classifier: Natural Language :: English
Classifier: Operating System :: MacOS
Classifier: Operating System :: POSIX :: Linux
Classifier: Operating System :: Microsoft :: Windows
Classifier: Programming Language :: Python :: 3.9
Classifier: Programming Language :: Python :: 3.10
Classifier: Programming Language :: Python :: 3.11
Classifier: Programming Language :: Python :: 3.12
Classifier: Programming Language :: Python :: 3.13
Classifier: Topic :: Scientific/Engineering :: Physics
Requires-Python: >=3.9
Requires-Dist: ray[default]<3,>=2.30
Requires-Dist: requests<3,>=2.32.2
Requires-Dist: importlib-metadata<9,>=5.2.0
Requires-Dist: qiskit[qpy-compat]<3,>=1.4
Requires-Dist: qiskit-ibm-runtime<1,>=0.40.1
Requires-Dist: cloudpickle==2.2.1
Requires-Dist: tqdm<5,>=4.66.3
Requires-Dist: opentelemetry-api<1.33.1,>=1.18.0
Requires-Dist: opentelemetry-sdk<1.33.1,>=1.18.0
Requires-Dist: opentelemetry-exporter-otlp-proto-grpc<1.33.1,>=1.18.0
Requires-Dist: opentelemetry-instrumentation-requests>=0.40b0
Requires-Dist: ipywidgets<9,>=8.1.6
Requires-Dist: ipython<9,>=8.10.0
Requires-Dist: numpy<3,>=1.17
Requires-Dist: pyarrow<19,>=16.0.0
Requires-Dist: aiohttp<4,>=3.10.0
Requires-Dist: zipp==3.19.1
Requires-Dist: certifi==2024.7.4
